blue_cli/__init__.py
blue_cli/blue.py
blue_cli/helper.py
blue_cli/manager.py
blue_cli/version
blue_cli/commands/__init__.py
blue_cli/commands/agent.py
blue_cli/commands/data.py
blue_cli/commands/json_utils.py
blue_cli/commands/platform.py
blue_cli/commands/profile.py
blue_cli/commands/registry.py
blue_cli/commands/service.py
blue_cli/commands/session.py
blue_cli/configs/images.json
blue_cli/configs/platform.json
blue_cli/configs/profile.json
blue_cli/configs/service.json
blue_cli/web/auth/out/404.html
blue_cli/web/auth/out/custom.css
blue_cli/web/auth/out/index.html
blue_cli/web/auth/out/_next/static/0XXf3895J64zZdEeS_FXR/_buildManifest.js
blue_cli/web/auth/out/_next/static/0XXf3895J64zZdEeS_FXR/_ssgManifest.js
blue_cli/web/auth/out/_next/static/Wf3gYuzM_rDUkmYHwd9Vn/_buildManifest.js
blue_cli/web/auth/out/_next/static/Wf3gYuzM_rDUkmYHwd9Vn/_ssgManifest.js
blue_cli/web/auth/out/_next/static/chunks/33bb9847-756503f4e534c4bb.js
blue_cli/web/auth/out/_next/static/chunks/43-4a96c3a1b1c2444f.js
blue_cli/web/auth/out/_next/static/chunks/blueprint-icons-16px-paths.b0266328dfb8a5c5.js
blue_cli/web/auth/out/_next/static/chunks/blueprint-icons-20px-paths.5ef4da70232ad1c8.js
blue_cli/web/auth/out/_next/static/chunks/blueprint-icons-all-paths-loader.89f339d5bddfd448.js
blue_cli/web/auth/out/_next/static/chunks/blueprint-icons-all-paths.048e84bea476acf1.js
blue_cli/web/auth/out/_next/static/chunks/blueprint-icons-split-paths-by-size-loader.baef99ce29f3c407.js
blue_cli/web/auth/out/_next/static/chunks/framework-ecc4130bc7a58a64.js
blue_cli/web/auth/out/_next/static/chunks/main-678ea17784401d5f.js
blue_cli/web/auth/out/_next/static/chunks/polyfills-78c92fac7aa8fdd8.js
blue_cli/web/auth/out/_next/static/chunks/webpack-86d53ca0a82c3fdd.js
blue_cli/web/auth/out/_next/static/chunks/pages/_app-a8ffedf03811cb1d.js
blue_cli/web/auth/out/_next/static/chunks/pages/_error-77823ddac6993d35.js
blue_cli/web/auth/out/_next/static/chunks/pages/index-90690a4243a6c4b6.js
blue_cli-1.0.dist-info/licenses/LICENSE
blue_cli-1.0.dist-info/METADATA
blue_cli-1.0.dist-info/WHEEL
blue_cli-1.0.dist-info/entry_points.txt
blue_cli-1.0.dist-info/top_level.txt
blue_cli-1.0.dist-info/RECORD
