Metadata-Version: 2.4
Name: blue-cli
Version: 1.0
Summary: Command line interface for blue installation and deployment
Author-email: Megagon Labs <blue@megagon.ai>
License-Expression: BSD-3-Clause
Project-URL: Homepage, https://github.com/megagonlabs/blue
Project-URL: Issues, https://github.com/megagonlabs/blue/issues
Project-URL: Discussions, https://github.com/megagonlabs/blue/discussions
Classifier: Development Status :: 4 - Beta
Classifier: Programming Language :: Python :: 3.9
Classifier: Operating System :: OS Independent
Requires-Python: >=3.9
License-File: LICENSE
Requires-Dist: blue-platform==1.0
Requires-Dist: click==8.2.1
Requires-Dist: tabulate==0.9.0
Requires-Dist: requests==2.31.0
Requires-Dist: websockets==11.0.3
Requires-Dist: nest_asyncio==1.6.0
Requires-Dist: traitlets==5.14.3
Requires-Dist: pydash==7.0.6
Requires-Dist: pandas==2.2.3
Requires-Dist: jsonmerge==1.9.2
Requires-Dist: jsonpath-ng==1.5.3
Requires-Dist: jsonschema==4.21.1
Requires-Dist: redis==5.2.0
Requires-Dist: docker==7.0.0
Requires-Dist: uuid==1.30
Dynamic: license-file
Dynamic: requires-dist
